{
  "legislative_session": "2025-2026",
  "identifier": "HF 3045",
  "title": "Property tax; state general levy for commercial-industrial property reduced.",
  "from_organization": "~{\"classification\": \"lower\"}",
  "classification": [
    "bill"
  ],
  "subject": [
    "Taxation-Property"
  ],
  "abstracts": [],
  "other_titles": [],
  "other_identifiers": [],
  "actions": [
    {
      "description": "Introduction and first reading, referred to Taxes",
      "date": "2025-04-02",
      "organization_id": "~{\"classification\": \"lower\"}",
      "classification": [
        "introduction",
        "referral-committee"
      ],
      "related_entities": [],
      "_processing": {
        "log_file_created": "2025-10-25T00:42:04Z"
      }
    }
  ],
  "sponsorships": [
    {
      "name": "Swedzinski",
      "classification": "primary",
      "entity_type": "person",
      "primary": true,
      "person_id": "~{\"name\": \"Swedzinski\"}",
      "organization_id": null
    },
    {
      "name": "Wiener",
      "classification": "cosponsor",
      "entity_type": "person",
      "primary": false,
      "person_id": "~{\"name\": \"Wiener\"}",
      "organization_id": null
    },
    {
      "name": "Joy",
      "classification": "cosponsor",
      "entity_type": "person",
      "primary": false,
      "person_id": "~{\"name\": \"Joy\"}",
      "organization_id": null
    }
  ],
  "related_bills": [
    {
      "identifier": "SF 3218",
      "legislative_session": "2025-2026",
      "relation_type": "companion"
    }
  ],
  "versions": [],
  "documents": [],
  "citations": [],
  "sources": [
    {
      "url": "https://www.revisor.mn.gov/bills/94/2025/0/HF/3045?body=House",
      "note": ""
    }
  ],
  "extras": {},
  "jurisdiction": {
    "id": "ocd-jurisdiction/country:us/state:mn/government",
    "name": "Minnesota",
    "classification": "state",
    "division_id": "ocd-division/country:us/state:mn"
  },
  "_processing": {
    "logs_latest_update": "2025-10-25T00:42:04Z",
    "text_extraction_latest_update": "2025-11-23T08:13:52.984190Z"
  }
}