{
  "legislative_session": "2025-2026",
  "identifier": "HF 3229",
  "title": "Spent fuel located at Prairie Island required to be transferred to another site for storage, additional storage authorized to be constructed at the Monticello nuclear generating plant, public utility authorized to withhold money from the renewable development account to pay for the cost to transport spent fuel.",
  "from_organization": "~{\"classification\": \"lower\"}",
  "classification": [
    "bill"
  ],
  "subject": [
    "Energy",
    "Fuels",
    "Public Utilities and Public Utilities Commission"
  ],
  "abstracts": [],
  "other_titles": [],
  "other_identifiers": [],
  "actions": [
    {
      "description": "Introduction and first reading, referred to Energy Finance and Policy",
      "date": "2025-04-23",
      "organization_id": "~{\"classification\": \"lower\"}",
      "classification": [
        "introduction",
        "referral-committee"
      ],
      "related_entities": [],
      "_processing": {
        "log_file_created": "2025-10-25T00:42:02Z"
      }
    },
    {
      "description": "Author added Skraba",
      "date": "2025-04-29",
      "organization_id": "~{\"classification\": \"lower\"}",
      "classification": [],
      "related_entities": [],
      "_processing": {
        "log_file_created": "2025-10-25T00:42:02Z"
      }
    }
  ],
  "sponsorships": [
    {
      "name": "Rarick",
      "classification": "primary",
      "entity_type": "person",
      "primary": true,
      "person_id": "~{\"name\": \"Rarick\"}",
      "organization_id": null
    },
    {
      "name": "Igo",
      "classification": "cosponsor",
      "entity_type": "person",
      "primary": false,
      "person_id": "~{\"name\": \"Igo\"}",
      "organization_id": null
    },
    {
      "name": "Skraba",
      "classification": "cosponsor",
      "entity_type": "person",
      "primary": false,
      "person_id": "~{\"name\": \"Skraba\"}",
      "organization_id": null
    }
  ],
  "related_bills": [
    {
      "identifier": "SF 3363",
      "legislative_session": "2025-2026",
      "relation_type": "companion"
    }
  ],
  "versions": [],
  "documents": [],
  "citations": [],
  "sources": [
    {
      "url": "https://www.revisor.mn.gov/bills/94/2025/0/HF/3229?body=House",
      "note": ""
    }
  ],
  "extras": {},
  "jurisdiction": {
    "id": "ocd-jurisdiction/country:us/state:mn/government",
    "name": "Minnesota",
    "classification": "state",
    "division_id": "ocd-division/country:us/state:mn"
  },
  "_processing": {
    "logs_latest_update": "2025-10-25T00:42:02Z",
    "text_extraction_latest_update": "2025-11-09T08:12:43.925817Z"
  }
}