{
  "legislative_session": "2025-2026",
  "identifier": "HF 1624",
  "title": "Mattress recycling program; assessment established for each mattress and box spring sold in the state to fund grants to local governments to expand mattress recycling programs, and money appropriated.",
  "from_organization": "~{\"classification\": \"lower\"}",
  "classification": [
    "bill"
  ],
  "subject": [
    "Environment"
  ],
  "abstracts": [],
  "other_titles": [],
  "other_identifiers": [],
  "actions": [
    {
      "description": "Introduction and first reading, referred to Environment and Natural Resources Finance and Policy",
      "date": "2025-02-27",
      "organization_id": "~{\"classification\": \"lower\"}",
      "classification": [
        "introduction",
        "referral-committee"
      ],
      "related_entities": [],
      "_processing": {
        "log_file_created": "2025-10-25T00:42:02Z"
      }
    },
    {
      "description": "Author added Rehrauer",
      "date": "2025-03-03",
      "organization_id": "~{\"classification\": \"lower\"}",
      "classification": [],
      "related_entities": [],
      "_processing": {
        "log_file_created": "2025-10-25T00:42:02Z"
      }
    },
    {
      "description": "Author added Hemmingsen-Jaeger",
      "date": "2025-03-05",
      "organization_id": "~{\"classification\": \"lower\"}",
      "classification": [],
      "related_entities": [],
      "_processing": {
        "log_file_created": "2025-10-25T00:42:02Z"
      }
    },
    {
      "description": "Author added Kraft",
      "date": "2025-04-01",
      "organization_id": "~{\"classification\": \"lower\"}",
      "classification": [],
      "related_entities": [],
      "_processing": {
        "log_file_created": "2025-10-25T00:42:02Z"
      }
    }
  ],
  "sponsorships": [
    {
      "name": "Jordan",
      "classification": "primary",
      "entity_type": "person",
      "primary": true,
      "person_id": "~{\"name\": \"Jordan\"}",
      "organization_id": null
    },
    {
      "name": "Agbaje",
      "classification": "cosponsor",
      "entity_type": "person",
      "primary": false,
      "person_id": "~{\"name\": \"Agbaje\"}",
      "organization_id": null
    },
    {
      "name": "Hansen, R.",
      "classification": "cosponsor",
      "entity_type": "person",
      "primary": false,
      "person_id": "~{\"name\": \"Hansen, R.\"}",
      "organization_id": null
    },
    {
      "name": "Rehrauer",
      "classification": "cosponsor",
      "entity_type": "person",
      "primary": false,
      "person_id": "~{\"name\": \"Rehrauer\"}",
      "organization_id": null
    },
    {
      "name": "Hemmingsen-Jaeger",
      "classification": "cosponsor",
      "entity_type": "person",
      "primary": false,
      "person_id": "~{\"name\": \"Hemmingsen-Jaeger\"}",
      "organization_id": null
    },
    {
      "name": "Kraft",
      "classification": "cosponsor",
      "entity_type": "person",
      "primary": false,
      "person_id": "~{\"name\": \"Kraft\"}",
      "organization_id": null
    }
  ],
  "related_bills": [
    {
      "identifier": "SF 1980",
      "legislative_session": "2025-2026",
      "relation_type": "companion"
    }
  ],
  "versions": [],
  "documents": [],
  "citations": [],
  "sources": [
    {
      "url": "https://www.revisor.mn.gov/bills/94/2025/0/HF/1624?body=House",
      "note": ""
    }
  ],
  "extras": {},
  "jurisdiction": {
    "id": "ocd-jurisdiction/country:us/state:mn/government",
    "name": "Minnesota",
    "classification": "state",
    "division_id": "ocd-division/country:us/state:mn"
  },
  "_processing": {
    "logs_latest_update": "2025-10-25T00:42:02Z",
    "text_extraction_latest_update": "2025-11-26T08:16:13.384848Z"
  }
}