{
  "legislative_session": "2025-2026",
  "identifier": "HF 1791",
  "title": "School district authorized to offer career and technical education postsecondary scholarships and postsecondary grants.",
  "from_organization": "~{\"classification\": \"lower\"}",
  "classification": [
    "bill"
  ],
  "subject": [
    "Education-Higher",
    "Education-School Districts"
  ],
  "abstracts": [],
  "other_titles": [],
  "other_identifiers": [],
  "actions": [
    {
      "description": "Introduction and first reading, referred to Education Finance",
      "date": "2025-03-03",
      "organization_id": "~{\"classification\": \"lower\"}",
      "classification": [
        "introduction",
        "referral-committee"
      ],
      "related_entities": [],
      "_processing": {
        "log_file_created": "2025-10-25T00:41:59Z"
      }
    }
  ],
  "sponsorships": [
    {
      "name": "Scott",
      "classification": "primary",
      "entity_type": "person",
      "primary": true,
      "person_id": "~{\"name\": \"Scott\"}",
      "organization_id": null
    },
    {
      "name": "Niska",
      "classification": "cosponsor",
      "entity_type": "person",
      "primary": false,
      "person_id": "~{\"name\": \"Niska\"}",
      "organization_id": null
    }
  ],
  "related_bills": [
    {
      "identifier": "SF 2139",
      "legislative_session": "2025-2026",
      "relation_type": "companion"
    }
  ],
  "versions": [],
  "documents": [],
  "citations": [],
  "sources": [
    {
      "url": "https://www.revisor.mn.gov/bills/94/2025/0/HF/1791?body=House",
      "note": ""
    }
  ],
  "extras": {},
  "jurisdiction": {
    "id": "ocd-jurisdiction/country:us/state:mn/government",
    "name": "Minnesota",
    "classification": "state",
    "division_id": "ocd-division/country:us/state:mn"
  },
  "_processing": {
    "logs_latest_update": "2025-10-25T00:41:59Z",
    "text_extraction_latest_update": "2025-12-05T08:16:02.370308Z"
  }
}