{
  "legislative_session": "2025-2026",
  "identifier": "HF 1836",
  "title": "State government; changes made to data practices.",
  "from_organization": "~{\"classification\": \"lower\"}",
  "classification": [
    "bill"
  ],
  "subject": [
    "Data Practices and Privacy",
    "Governmental Operations-State"
  ],
  "abstracts": [],
  "other_titles": [],
  "other_identifiers": [],
  "actions": [
    {
      "description": "Introduction and first reading, referred to Judiciary Finance and Civil Law",
      "date": "2025-03-03",
      "organization_id": "~{\"classification\": \"lower\"}",
      "classification": [
        "introduction",
        "referral-committee"
      ],
      "related_entities": [],
      "_processing": {
        "log_file_created": "2025-10-25T00:42:03Z"
      }
    },
    {
      "description": "Committee report, to adopt as amended and re-refer to State Government Finance and Policy",
      "date": "2025-03-24",
      "organization_id": "~{\"classification\": \"lower\"}",
      "classification": [
        "committee-passage"
      ],
      "related_entities": [],
      "_processing": {
        "log_file_created": "2025-10-25T00:42:03Z"
      }
    }
  ],
  "sponsorships": [
    {
      "name": "Klevorn",
      "classification": "primary",
      "entity_type": "person",
      "primary": true,
      "person_id": "~{\"name\": \"Klevorn\"}",
      "organization_id": null
    },
    {
      "name": "Howard",
      "classification": "cosponsor",
      "entity_type": "person",
      "primary": false,
      "person_id": "~{\"name\": \"Howard\"}",
      "organization_id": null
    },
    {
      "name": "Bahner",
      "classification": "cosponsor",
      "entity_type": "person",
      "primary": false,
      "person_id": "~{\"name\": \"Bahner\"}",
      "organization_id": null
    }
  ],
  "related_bills": [
    {
      "identifier": "SF 2089",
      "legislative_session": "2025-2026",
      "relation_type": "companion"
    }
  ],
  "versions": [],
  "documents": [],
  "citations": [],
  "sources": [
    {
      "url": "https://www.revisor.mn.gov/bills/94/2025/0/HF/1836?body=House",
      "note": ""
    }
  ],
  "extras": {},
  "jurisdiction": {
    "id": "ocd-jurisdiction/country:us/state:mn/government",
    "name": "Minnesota",
    "classification": "state",
    "division_id": "ocd-division/country:us/state:mn"
  },
  "_processing": {
    "logs_latest_update": "2025-10-25T00:42:03Z",
    "text_extraction_latest_update": "2025-12-08T08:18:43.031989Z"
  }
}